{
  "name": "multi_megatower1_0_floor3",
  "refpalette": "c70cities:multi_megatower1_0_floor3_palette",
  "xsize": 16,
  "zsize": 16,
  "slices": [
    [
      "                ",
      "                ",
      "                ",
      "                ",
      "                ",
      "                ",
      "                ",
      "                ",
      "                ",
      "                ",
      "                ",
      "             a  ",
      "             bcc",
      "           abdee",
      "            fe  ",
      "            fe  "
    ],
    [
      "                ",
      "                ",
      "                ",
      "                ",
      "                ",
      "                ",
      "                ",
      "                ",
      "                ",
      "                ",
      "                ",
      "             a  ",
      "             bcc",
      "           abdgg",
      "            fh  ",
      "            fh  "
    ],
    [
      "                ",
      "                ",
      "                ",
      "                ",
      "                ",
      "                ",
      "                ",
      "                ",
      "                ",
      "                ",
      "                ",
      "             a  ",
      "             bcc",
      "           abdgg",
      "            fhii",
      "            fhij"
    ],
    [
      "                ",
      "                ",
      "                ",
      "                ",
      "                ",
      "                ",
      "                ",
      "                ",
      "                ",
      "                ",
      "                ",
      "             a  ",
      "             bcc",
      "           abdgg",
      "            fhii",
      "            fhii"
    ],
    [
      "                ",
      "                ",
      "                ",
      "                ",
      "                ",
      "                ",
      "                ",
      "                ",
      "                ",
      "                ",
      "                ",
      "             a  ",
      "             bcc",
      "           abdgg",
      "            fk  ",
      "            fk  "
    ],
    [
      "                ",
      "                ",
      "                ",
      "                ",
      "                ",
      "                ",
      "                ",
      "                ",
      "                ",
      "                ",
      "                ",
      "             a  ",
      "             bcc",
      "           abdll",
      "            fm  ",
      "            fm  "
    ]
  ]
}