{
  "name": "multi_laboratory1_10_top",
  "refpalette": "c70cities:multi_laboratory1_10_top_palette",
  "xsize": 16,
  "zsize": 16,
  "slices": [
    [
      "                ",
      "                ",
      "aaaaa           ",
      "     aa         ",
      "      a         ",
      "bbbbb  a        ",
      "    b  a        ",
      "ccc b  a        ",
      "  c b  a        ",
      "  c b  a        ",
      "d c b  a        ",
      "  c b  e        ",
      "  c b  e        ",
      "ccc b  e        ",
      "    b           ",
      "bbbbb           "
    ],
    [
      "                ",
      "                ",
      "aaaaa           ",
      "     aa         ",
      "      a         ",
      "       e        ",
      "       e        ",
      "       e        ",
      "                ",
      "                ",
      "                ",
      "                ",
      "                ",
      "                ",
      "                ",
      "                "
    ],
    [
      "                ",
      "                ",
      "                ",
      "                ",
      "                ",
      "                ",
      "                ",
      "                ",
      "                ",
      "                ",
      "                ",
      "                ",
      "                ",
      "                ",
      "                ",
      "                "
    ],
    [
      "                ",
      "                ",
      "                ",
      "                ",
      "                ",
      "                ",
      "                ",
      "                ",
      "                ",
      "                ",
      "                ",
      "                ",
      "                ",
      "                ",
      "                ",
      "                "
    ],
    [
      "                ",
      "                ",
      "                ",
      "                ",
      "                ",
      "                ",
      "                ",
      "                ",
      "                ",
      "                ",
      "                ",
      "                ",
      "                ",
      "                ",
      "                ",
      "                "
    ],
    [
      "                ",
      "                ",
      "                ",
      "                ",
      "                ",
      "                ",
      "                ",
      "                ",
      "                ",
      "                ",
      "                ",
      "                ",
      "                ",
      "                ",
      "                ",
      "                "
    ]
  ]
}