{
  "name": "multi_megatower1_0_floor6",
  "refpalette": "c70cities:multi_megatower1_0_floor6_palette",
  "xsize": 16,
  "zsize": 16,
  "slices": [
    [
      "                ",
      "                ",
      "                ",
      "                ",
      "                ",
      "                ",
      "                ",
      "                ",
      "                ",
      "                ",
      "                ",
      "             a b",
      "             cdd",
      "           aceff",
      "            df  ",
      "           gdf  "
    ],
    [
      "                ",
      "                ",
      "                ",
      "                ",
      "                ",
      "                ",
      "                ",
      "                ",
      "                ",
      "                ",
      "                ",
      "             a b",
      "             c  ",
      "           acehh",
      "             i  ",
      "           g i  "
    ],
    [
      "                ",
      "                ",
      "                ",
      "                ",
      "                ",
      "                ",
      "                ",
      "                ",
      "                ",
      "                ",
      "                ",
      "             a b",
      "             c  ",
      "           acehh",
      "             ijj",
      "           g ijk"
    ],
    [
      "                ",
      "                ",
      "                ",
      "                ",
      "                ",
      "                ",
      "                ",
      "                ",
      "                ",
      "                ",
      "                ",
      "             a b",
      "             cb ",
      "           acehh",
      "            gijj",
      "           g ijj"
    ],
    [
      "                ",
      "                ",
      "                ",
      "                ",
      "                ",
      "                ",
      "                ",
      "                ",
      "                ",
      "                ",
      "                ",
      "             a b",
      "             cb ",
      "           acehh",
      "            gl  ",
      "           g l  "
    ],
    [
      "                ",
      "                ",
      "                ",
      "                ",
      "                ",
      "                ",
      "                ",
      "                ",
      "                ",
      "                ",
      "                ",
      "             a b",
      "             cb ",
      "           acemm",
      "            gn  ",
      "           g n  "
    ]
  ]
}