{
  "type": "pfm:furniture",
  "group": "kitchen",
  "ingredients": [
    {
      "item": "minecraft:polished_deepslate"
    },
    {
      "item": "minecraft:polished_deepslate"
    },
    {
      "item": "minecraft:polished_deepslate"
    },
    {
      "item": "minecraft:polished_deepslate"
    },
    {
      "item": "minecraft:polished_deepslate"
    },
    {
      "item": "minecraft:polished_deepslate"
    },
    {
      "item": "minecraft:polished_deepslate"
    },
    {
      "item": "minecraft:polished_deepslate"
    },
    {
      "item": "minecraft:chest"
    }
  ],
  "result": {
    "item": "pfm:deepslate_kitchen_wall_drawer"
  }
}