{
  "type": "pfm:furniture",
  "group": "bedroom",
  "ingredients": [
    {
      "item": "minecraft:diorite"
    },
    {
      "item": "minecraft:diorite"
    },
    {
      "item": "minecraft:diorite"
    },
    {
      "item": "minecraft:diorite"
    },
    {
      "item": "minecraft:diorite"
    },
    {
      "item": "minecraft:diorite"
    },
    {
      "item": "minecraft:polished_diorite"
    },
    {
      "item": "minecraft:chest"
    }
  ],
  "result": {
    "item": "pfm:diorite_classic_nightstand",
    "count": 4
  }
}