{
  "name": "multi_hospital_1_base1_palette",
  "palette": [
    {
      "char": "a",
      "block": "minecraft:dirt"
    },
    {
      "char": "b",
      "block": "embellishcraft:smooth_marble"
    },
    {
      "char": "c",
      "block": "embellishcraft:polished_marble"
    },
    {
      "char": "d",
      "block": "minecraft:polished_andesite"
    },
    {
      "char": "e",
      "block": "minecraft:smooth_stone"
    },
    {
      "char": "f",
      "block": "minecraft:smooth_stone_slab[type=top,waterlogged=false]"
    },
    {
      "char": "g",
      "block": "minecraft:quartz_stairs[waterlogged=false,half=top,facing=east,shape=straight]"
    },
    {
      "char": "h",
      "block": "minecraft:quartz_block"
    },
    {
      "char": "i",
      "block": "minecraft:quartz_stairs[waterlogged=false,half=top,facing=west,shape=straight]"
    },
    {
      "char": "j",
      "block": "quark:stone_brick_vertical_slab[type=east,waterlogged=false]"
    },
    {
      "char": "k",
      "block": "zombie_extreme:iron_table[facing=east]"
    },
    {
      "char": "l",
      "block": "create:polished_cut_limestone_slab[type=top,waterlogged=false]"
    },
    {
      "char": "m",
      "block": "zombie_extreme:iron_table[facing=west]"
    },
    {
      "char": "n",
      "block": "zombie_extreme:iron_table[facing=north]"
    },
    {
      "char": "o",
      "block": "minecraft:bookshelf"
    },
    {
      "char": "p",
      "block": "quark:stone_brick_vertical_slab[type=north,waterlogged=false]"
    },
    {
      "char": "q",
      "block": "quark:quartz_vertical_slab[type=east,waterlogged=false]"
    },
    {
      "char": "r",
      "block": "quark:quartz_vertical_slab[type=north,waterlogged=false]"
    },
    {
      "char": "s",
      "block": "minecraft:quartz_stairs[waterlogged=false,half=bottom,facing=west,shape=straight]"
    },
    {
      "char": "t",
      "block": "minecraft:rail[waterlogged=false,shape=north_south]"
    },
    {
      "char": "u",
      "block": "minecraft:quartz_stairs[waterlogged=false,half=bottom,facing=east,shape=straight]"
    },
    {
      "char": "w",
      "block": "minecraft:smooth_stone_slab[type=bottom,waterlogged=false]"
    },
    {
      "char": "x",
      "block": "embellishcraft:white_pillow[waterlogged=false,occupied=false,part=head,facing=west]"
    },
    {
      "char": "y",
      "block": "apocalypsenow:medical_storage[waterlogged=false,facing=north]",
      "loot": "chestloot"
    },
    {
      "char": "A",
      "block": "simplylight:illuminant_panel[waterlogged=false,facing=down]"
    },
    {
      "char": "B",
      "block": "minecraft:redstone_torch[lit=true]"
    },
    {
      "char": "C",
      "block": "minecraft:quartz_slab[type=bottom,waterlogged=false]"
    },
    {
      "char": "D",
      "block": "minecraft:quartz_slab[type=top,waterlogged=false]"
    }
  ]
}