{
  "name": "multi_communitycenter_3_ground_palette",
  "palette": [
    {
      "char": "a",
      "block": "embellishcraft:polished_paving"
    },
    {
      "char": "b",
      "block": "minecraft:moss_block"
    },
    {
      "char": "c",
      "block": "minecraft:quartz_block"
    },
    {
      "char": "d",
      "block": "minecraft:dirt"
    },
    {
      "char": "e",
      "block": "create:polished_cut_calcite"
    },
    {
      "char": "f",
      "block": "minecraft:water[level=0]"
    },
    {
      "char": "g",
      "block": "minecraft:polished_andesite"
    },
    {
      "char": "h",
      "block": "minecraft:birch_planks"
    },
    {
      "char": "i",
      "block": "cfm:andesite_table[waterlogged=false]"
    },
    {
      "char": "j",
      "block": "create:cut_calcite"
    },
    {
      "char": "k",
      "block": "minecraft:red_carpet"
    },
    {
      "char": "l",
      "block": "minecraft:birch_stairs[waterlogged=false,half=top,facing=east,shape=straight]"
    },
    {
      "char": "m",
      "block": "another_furniture:white_stool[waterlogged=false]"
    },
    {
      "char": "n",
      "block": "minecraft:dark_oak_leaves[persistent=true]"
    },
    {
      "char": "o",
      "block": "create:cut_calcite_slab[type=bottom,waterlogged=false]"
    },
    {
      "char": "p",
      "block": "minecraft:dead_bush"
    },
    {
      "char": "q",
      "block": "quark:dark_oak_hedge[waterlogged=false]"
    },
    {
      "char": "r",
      "block": "minecraft:smooth_stone_slab[type=bottom,waterlogged=false]"
    },
    {
      "char": "s",
      "block": "minecraft:rose_bush[half=lower]"
    },
    {
      "char": "t",
      "block": "create:polished_cut_calcite_wall[waterlogged=false,up=true]"
    },
    {
      "char": "u",
      "block": "minecraft:tall_grass[half=lower]"
    },
    {
      "char": "w",
      "block": "minecraft:dark_oak_planks"
    },
    {
      "char": "x",
      "block": "create:dark_oak_window_pane[waterlogged=false]"
    },
    {
      "char": "y",
      "block": "minecraft:smooth_quartz"
    },
    {
      "char": "A",
      "block": "minecraft:bookshelf"
    },
    {
      "char": "B",
      "block": "minecraft:heavy_weighted_pressure_plate"
    },
    {
      "char": "C",
      "block": "minecraft:rose_bush[half=upper]"
    },
    {
      "char": "D",
      "block": "minecraft:tall_grass[half=upper]"
    },
    {
      "char": "E",
      "block": "minecraft:stripped_dark_oak_log[axis=y]"
    },
    {
      "char": "F",
      "block": "minecraft:smooth_stone_slab[type=top,waterlogged=false]"
    },
    {
      "char": "I",
      "block": "create:vertical_framed_glass_pane[waterlogged=false]"
    },
    {
      "char": "J",
      "block": "quark:smooth_quartz_vertical_slab[type=north,waterlogged=false]"
    },
    {
      "char": "K",
      "block": "minecraft:dark_oak_slab[type=bottom,waterlogged=false]"
    }
  ]
}