{
  "name": "multi_megatower1_3_floor14_palette",
  "palette": [
    {
      "char": "a",
      "block": "create:cut_limestone_bricks"
    },
    {
      "char": "b",
      "block": "create:polished_cut_limestone"
    },
    {
      "char": "c",
      "block": "create:cut_limestone_brick_slab[type=bottom,waterlogged=false]"
    },
    {
      "char": "d",
      "block": "minecraft:moss_block"
    },
    {
      "char": "e",
      "block": "minecraft:mossy_cobblestone"
    },
    {
      "char": "f",
      "block": "minecraft:birch_planks"
    },
    {
      "char": "g",
      "block": "embellishcraft:smooth_marble"
    },
    {
      "char": "h",
      "block": "quark:calcite_bricks"
    },
    {
      "char": "i",
      "block": "create:framed_glass"
    },
    {
      "char": "j",
      "block": "create:polished_cut_limestone_slab[type=bottom,waterlogged=false]"
    },
    {
      "char": "k",
      "block": "simplylight:wall_lamp[waterlogged=false,facing=south]"
    },
    {
      "char": "l",
      "block": "quark:calcite_bricks_vertical_slab[type=north,waterlogged=false]"
    },
    {
      "char": "m",
      "block": "another_furniture:birch_planter_box[type=right,attached=false,facing=north]"
    },
    {
      "char": "n",
      "block": "another_furniture:birch_planter_box[type=middle,attached=false,facing=north]"
    },
    {
      "char": "o",
      "block": "another_furniture:birch_planter_box[type=left,attached=false,facing=north]"
    },
    {
      "char": "p",
      "block": "quark:calcite_bricks_vertical_slab[type=east,waterlogged=false]"
    },
    {
      "char": "q",
      "block": "minecraft:cyan_terracotta"
    }
  ]
}