{
  "name": "multi_factory_0_ground_palette",
  "palette": [
    {
      "char": "a",
      "block": "minecraft:cobblestone"
    },
    {
      "char": "b",
      "block": "minecraft:smooth_stone"
    },
    {
      "char": "c",
      "block": "embellishcraft:light_gray_corrugated_metal_plate"
    },
    {
      "char": "d",
      "block": "immersiveengineering:steel_scaffolding_standard[waterlogged=false]"
    },
    {
      "char": "e",
      "block": "minecraft:chest",
      "loot": "chestloot"
    },
    {
      "char": "f",
      "block": "minecraft:barrel[facing=south,open=false]"
    },
    {
      "char": "g",
      "block": "quark:stone_vertical_slab[waterlogged=false,type=east]"
    },
    {
      "char": "h",
      "block": "cfm:stripped_birch_kitchen_sink_light[facing=north]"
    },
    {
      "char": "i",
      "block": "embellishcraft:steel_door[hinge=right,half=lower,facing=west,open=false]"
    },
    {
      "char": "j",
      "block": "biomesoplenty:dead_pressure_plate"
    },
    {
      "char": "k",
      "block": "biomesoplenty:dead_door[hinge=right,half=lower,facing=east,open=false]"
    },
    {
      "char": "l",
      "block": "minecraft:quartz_stairs[waterlogged=false,half=top,shape=straight,facing=east]"
    },
    {
      "char": "m",
      "block": "minecraft:stone"
    },
    {
      "char": "n",
      "block": "quark:stone_vertical_slab[waterlogged=false,type=north]"
    },
    {
      "char": "o",
      "block": "cfm:cyan_kitchen_counter[facing=west,type=default]"
    },
    {
      "char": "p",
      "block": "biomesoplenty:dead_door[hinge=left,half=lower,facing=east,open=false]"
    },
    {
      "char": "q",
      "block": "cfm:stone_chair[waterlogged=false,facing=east]"
    },
    {
      "char": "r",
      "block": "cfm:stripped_birch_kitchen_sink_light[facing=south]"
    },
    {
      "char": "s",
      "block": "quark:stone_vertical_slab[waterlogged=false,type=south]"
    },
    {
      "char": "t",
      "block": "cfm:stone_chair[waterlogged=false,facing=north]"
    },
    {
      "char": "u",
      "block": "embellishcraft:steel_rungs[waterlogged=false,facing=west]"
    },
    {
      "char": "w",
      "block": "minecraft:stonecutter[facing=north]"
    },
    {
      "char": "x",
      "block": "cfm:cyan_kitchen_counter[facing=south,type=default]"
    },
    {
      "char": "y",
      "block": "minecraft:grindstone[face=floor,facing=south]"
    },
    {
      "char": "A",
      "block": "embellishcraft:steel_door[hinge=right,half=lower,facing=north,open=false]"
    },
    {
      "char": "B",
      "block": "immersiveengineering:light_engineering"
    },
    {
      "char": "C",
      "block": "minecraft:cobweb"
    },
    {
      "char": "D",
      "block": "minecraft:repeating_command_block[conditional=false,facing=west]"
    },
    {
      "char": "E",
      "block": "immersiveengineering:rs_engineering"
    },
    {
      "char": "F",
      "block": "embellishcraft:steel_door[hinge=right,half=upper,facing=west,open=false]"
    },
    {
      "char": "I",
      "block": "biomesoplenty:dead_door[hinge=right,half=upper,facing=east,open=false]"
    },
    {
      "char": "J",
      "block": "biomesoplenty:dead_trapdoor[waterlogged=false,half=bottom,facing=west,open=true]"
    },
    {
      "char": "K",
      "block": "create:vertical_framed_glass_pane[waterlogged=false]"
    },
    {
      "char": "L",
      "block": "minecraft:redstone_torch[lit=true]"
    },
    {
      "char": "M",
      "block": "biomesoplenty:dead_door[hinge=left,half=upper,facing=east,open=false]"
    },
    {
      "char": "N",
      "block": "minecraft:comparator[facing=east]"
    },
    {
      "char": "O",
      "block": "minecraft:repeater[facing=west]"
    },
    {
      "char": "P",
      "block": "embellishcraft:steel_door[hinge=right,half=upper,facing=north,open=false]"
    },
    {
      "char": "Q",
      "block": "immersiveengineering:conveyor_basic[waterlogged=false,facing=south]"
    },
    {
      "char": "R",
      "block": "clickmachine:auto_clicker[facing=east]",
      "tag": {
        "speed_index": 8,
        "right_click": 1,
        "inv": {
          "Size": 1,
          "Items": [
            {
              "Slot": 0,
              "id": "immersiveengineering:hammer",
              "Count": 1
            }
          ]
        },
        "id": "clickmachine:tile"
      }
    },
    {
      "char": "S",
      "block": "minecraft:piston[facing=down]"
    },
    {
      "char": "T",
      "block": "immersiveengineering:steel_fence[waterlogged=false]"
    },
    {
      "char": "U",
      "block": "embellishcraft:light_gray_corrugated_metal_plate_stairs[waterlogged=false,half=top,shape=straight,facing=west]"
    },
    {
      "char": "V",
      "block": "embellishcraft:light_gray_corrugated_metal_plate_slab[waterlogged=false,type=top]"
    },
    {
      "char": "W",
      "block": "embellishcraft:light_gray_corrugated_metal_plate_stairs[waterlogged=false,half=top,shape=straight,facing=east]"
    },
    {
      "char": "X",
      "block": "quark:smooth_stone_vertical_slab[waterlogged=false,type=west]"
    },
    {
      "char": "Y",
      "block": "immersiveengineering:heavy_engineering"
    },
    {
      "char": "Z",
      "block": "minecraft:hopper[facing=down]"
    },
    {
      "char": "0",
      "block": "embellishcraft:gray_corrugated_metal_plate_slab[waterlogged=false,type=bottom]"
    },
    {
      "char": "1",
      "block": "biomesoplenty:stripped_dead_log[axis=z]"
    },
    {
      "char": "2",
      "block": "immersiveengineering:connector_mv[waterlogged=false,facing=down]"
    },
    {
      "char": "3",
      "block": "minecraft:smooth_stone_slab[waterlogged=false,type=bottom]"
    }
  ]
}