{
  "name": "multi_megatower1_6_floor9_palette",
  "palette": [
    {
      "char": "a",
      "block": "minecraft:spruce_fence[waterlogged=false]"
    },
    {
      "char": "b",
      "block": "quark:spruce_vertical_slab[type=east,waterlogged=false]"
    },
    {
      "char": "c",
      "block": "minecraft:spruce_planks"
    },
    {
      "char": "d",
      "block": "quark:spruce_vertical_slab[type=west,waterlogged=false]"
    },
    {
      "char": "e",
      "block": "minecraft:birch_slab[type=top,waterlogged=false]"
    },
    {
      "char": "f",
      "block": "minecraft:birch_stairs[waterlogged=false,half=top,facing=south,shape=straight]"
    },
    {
      "char": "g",
      "block": "quark:spruce_vertical_slab[type=south,waterlogged=false]"
    },
    {
      "char": "h",
      "block": "minecraft:birch_planks"
    },
    {
      "char": "i",
      "block": "minecraft:stripped_oak_log[axis=y]"
    },
    {
      "char": "j",
      "block": "minecraft:birch_stairs[waterlogged=false,half=top,facing=west,shape=straight]"
    },
    {
      "char": "k",
      "block": "quark:spruce_vertical_slab[type=north,waterlogged=false]"
    },
    {
      "char": "l",
      "block": "quark:polished_calcite_vertical_slab[type=north,waterlogged=false]"
    },
    {
      "char": "m",
      "block": "farmersdelight:potato_crate"
    },
    {
      "char": "n",
      "block": "quark:polished_calcite_vertical_slab[type=east,waterlogged=false]"
    },
    {
      "char": "o",
      "block": "farmersdelight:carrot_crate"
    },
    {
      "char": "p",
      "block": "minecraft:cobweb"
    },
    {
      "char": "q",
      "block": "minecraft:smooth_stone_slab[type=top,waterlogged=false]"
    },
    {
      "char": "r",
      "block": "embellishcraft:polished_basalt_slab[type=top,waterlogged=false]"
    },
    {
      "char": "s",
      "block": "minecraft:stripped_oak_log[axis=x]"
    },
    {
      "char": "t",
      "block": "embellishcraft:air_duct"
    },
    {
      "char": "u",
      "block": "minecraft:stripped_oak_log[axis=z]"
    },
    {
      "char": "w",
      "block": "minecraft:chain[waterlogged=false,axis=y]"
    }
  ]
}