{
  "name": "multi_megatower1_1_floor8_palette",
  "palette": [
    {
      "char": "a",
      "block": "quark:spruce_vertical_slab[waterlogged=false,type=north]"
    },
    {
      "char": "b",
      "block": "minecraft:birch_slab[waterlogged=false,type=top]"
    },
    {
      "char": "c",
      "block": "minecraft:birch_planks"
    },
    {
      "char": "d",
      "block": "quark:spruce_vertical_slab[waterlogged=false,type=south]"
    },
    {
      "char": "e",
      "block": "biomesoplenty:smooth_white_sandstone_stairs[waterlogged=false,half=top,shape=straight,facing=south]"
    },
    {
      "char": "f",
      "block": "biomesoplenty:smooth_white_sandstone_stairs[waterlogged=false,half=bottom,shape=straight,facing=south]"
    },
    {
      "char": "g",
      "block": "biomesoplenty:smooth_white_sandstone"
    },
    {
      "char": "h",
      "block": "minecraft:spruce_fence[waterlogged=false]"
    },
    {
      "char": "i",
      "block": "minecraft:spruce_planks"
    },
    {
      "char": "j",
      "block": "minecraft:stripped_oak_log[axis=y]"
    },
    {
      "char": "k",
      "block": "minecraft:birch_stairs[waterlogged=false,half=bottom,shape=straight,facing=north]"
    },
    {
      "char": "l",
      "block": "minecraft:moss_block"
    },
    {
      "char": "m",
      "block": "quark:calcite_bricks_vertical_slab[waterlogged=false,type=west]"
    },
    {
      "char": "n",
      "block": "biomesoplenty:smooth_white_sandstone_stairs[waterlogged=false,half=bottom,shape=straight,facing=north]"
    },
    {
      "char": "o",
      "block": "embellishcraft:spruce_plain_door[hinge=left,half=lower,facing=south,open=false]"
    },
    {
      "char": "p",
      "block": "create:andesite_bars[waterlogged=false]"
    },
    {
      "char": "q",
      "block": "minecraft:moss_carpet"
    },
    {
      "char": "r",
      "block": "quark:spruce_leaf_carpet"
    },
    {
      "char": "s",
      "block": "embellishcraft:spruce_plain_door[hinge=left,half=upper,facing=south,open=false]"
    },
    {
      "char": "t",
      "block": "biomesoplenty:smooth_white_sandstone_stairs[waterlogged=false,half=top,shape=straight,facing=north]"
    },
    {
      "char": "u",
      "block": "minecraft:redstone_wall_torch[lit=true,facing=north]"
    },
    {
      "char": "w",
      "block": "minecraft:stripped_oak_log[axis=z]"
    },
    {
      "char": "x",
      "block": "minecraft:stripped_oak_log[axis=x]"
    }
  ]
}